gitgenius/__init__.py
gitgenius/admin.py
gitgenius/cli.py
gitgenius/config.py
gitgenius/db.py
gitgenius/error_db.py
gitgenius/examples.py
gitgenius/explainer.py
gitgenius-0.1.3.dist-info/licenses/LICENSE
gitgenius-0.1.3.dist-info/METADATA
gitgenius-0.1.3.dist-info/WHEEL
gitgenius-0.1.3.dist-info/entry_points.txt
gitgenius-0.1.3.dist-info/top_level.txt
gitgenius-0.1.3.dist-info/RECORD
